{"name":"template","plan":"Hobby","schema":[{"apiId":"API#f308e14d-6f2a-4fc3-95c7-718c8e950d86","apiName":"メンバー","apiDescription":null,"apiEndpoint":"members","apiType":"LIST","apiFields":[{"idValue":"QLcrizKf89","fieldId":"name","name":"名前","kind":"text","required":true,"isUnique":false},{"idValue":"vns46ipqmo","fieldId":"position","name":"役職","kind":"text","required":true,"isUnique":false},{"idValue":"rdnqJuU-2s","fieldId":"profile","name":"プロフィール","kind":"textArea","required":true,"textSizeLimitValidation":{"textSize":{"min":null,"max":500}}},{"idValue":"ESU2UqPxfG","fieldId":"image","name":"画像","kind":"media","required":true}],"customFields":[]},{"apiId":"API#06e0b168-6893-4aed-b21e-2f191667de9b","apiName":"ニュース","apiDescription":null,"apiEndpoint":"news","apiType":"LIST","apiFields":[{"idValue":"7fJ4wmFaXH","fieldId":"title","name":"タイトル","kind":"text","required":true,"isUnique":false},{"idValue":"L5otMF9i4Q","fieldId":"description","name":"概要","kind":"textArea","required":true,"textSizeLimitValidation":{"textSize":{"min":null,"max":200}}},{"idValue":"-kxDC3NxMT","fieldId":"content","name":"内容","kind":"richEditorV2","required":true},{"idValue":"lUucv2NGFO","fieldId":"category","name":"カテゴリー","kind":"relation","referenceKey":"API#be8c6235-c130-4c7e-8fe8-28775955d3e2"},{"idValue":"k3BkNMiB_c","fieldId":"thumbnail","name":"サムネイル画像","kind":"media","description":"1200×630のサイズで入稿してください。SNSシェア時のOGP画像として使用されます。","imageSizeValidation":{"imageSize":{"width":1200,"height":630}}}],"customFields":[]},{"apiId":"API#be8c6235-c130-4c7e-8fe8-28775955d3e2","apiName":"カテゴリー","apiDescription":"ニュース用のカテゴリーです。","apiEndpoint":"categories","apiType":"LIST","apiFields":[{"idValue":"n1oYZpyjl7","fieldId":"name","name":"カテゴリー名","kind":"text","required":true,"isUnique":false}],"customFields":[]}]}